automailer/__init__.py
automailer/__main__.py
automailer/app.py
automailer/client.py
automailer-0.1.3.dist-info/entry_points.txt
automailer-0.1.3.dist-info/WHEEL
automailer-0.1.3.dist-info/METADATA
automailer-0.1.3.dist-info/RECORD
